eolian/__init__.py
eolian/database/__init__.py
eolian/database/models/__init__.py
eolian/database/models/cetasa/__init__.py
eolian/database/models/cetasa/magana.py
eolian/database/models/cetasa/met.py
eolian/database/models/cetasa/oncala.py
eolian/database/models/plc/__init__.py
eolian/database/models/plc/plc.py
eolian/database/timescale.py
eolian/utils.py
eolian-1.0.dist-info/LICENSE
eolian-1.0.dist-info/WHEEL
eolian-1.0.dist-info/METADATA
eolian-1.0.dist-info/RECORD
